ErisPulse_HelpModule/Core.py
ErisPulse_HelpModule/__init__.py
erispulse_helpmodule-2.0.0.dist-info/licenses/LICENSE
erispulse_helpmodule-2.0.0.dist-info/METADATA
erispulse_helpmodule-2.0.0.dist-info/WHEEL
erispulse_helpmodule-2.0.0.dist-info/entry_points.txt
erispulse_helpmodule-2.0.0.dist-info/top_level.txt
erispulse_helpmodule-2.0.0.dist-info/RECORD
