Metadata-Version: 2.4
Name: ErisPulse-HelpModule
Version: 2.0.0
Summary: ErisPulse 帮助命令模块，提供自动化的命令帮助系统，支持查看所有可用命令及其用法说明
Author-email: wsu2059q <wsu2059@qq.com>
License: Copyright 2025 wsu2059q
Project-URL: homepage, https://github.com/wsu2059q/ErisPulse-HelpModule
Requires-Python: >=3.10
License-File: LICENSE
Dynamic: license-file
